[
  {
    "generated_at": "2026-04-18T20:01:42Z",
    "anchor_date": "2026-04-18",
    "forecast": [
      {
        "day": 1,
        "date": "2026-04-19",
        "flow_m3s": 2658.8,
        "level_m": 21.779
      },
      {
        "day": 2,
        "date": "2026-04-20",
        "flow_m3s": 2771.0,
        "level_m": 21.852
      },
      {
        "day": 3,
        "date": "2026-04-21",
        "flow_m3s": 2702.4,
        "level_m": 21.951
      },
      {
        "day": 4,
        "date": "2026-04-22",
        "flow_m3s": 2829.8,
        "level_m": 22.136
      },
      {
        "day": 5,
        "date": "2026-04-23",
        "flow_m3s": 2892.0,
        "level_m": 22.048
      },
      {
        "day": 6,
        "date": "2026-04-24",
        "flow_m3s": 2833.3,
        "level_m": 22.029
      },
      {
        "day": 7,
        "date": "2026-04-25",
        "flow_m3s": 2769.6,
        "level_m": 21.979
      },
      {
        "day": 8,
        "date": "2026-04-26",
        "flow_m3s": 2690.7,
        "level_m": 21.86
      },
      {
        "day": 9,
        "date": "2026-04-27",
        "flow_m3s": 2597.0,
        "level_m": 21.703
      },
      {
        "day": 10,
        "date": "2026-04-28",
        "flow_m3s": 2472.9,
        "level_m": 21.627
      }
    ]
  },
  {
    "generated_at": "2026-04-19T20:01:30Z",
    "anchor_date": "2026-04-19",
    "forecast": [
      {
        "day": 1,
        "date": "2026-04-20",
        "flow_m3s": 2745.3,
        "level_m": 21.873
      },
      {
        "day": 2,
        "date": "2026-04-21",
        "flow_m3s": 2782.2,
        "level_m": 21.941
      },
      {
        "day": 3,
        "date": "2026-04-22",
        "flow_m3s": 2744.9,
        "level_m": 21.887
      },
      {
        "day": 4,
        "date": "2026-04-23",
        "flow_m3s": 2767.0,
        "level_m": 22.213
      },
      {
        "day": 5,
        "date": "2026-04-24",
        "flow_m3s": 2840.4,
        "level_m": 22.003
      },
      {
        "day": 6,
        "date": "2026-04-25",
        "flow_m3s": 2734.4,
        "level_m": 21.929
      },
      {
        "day": 7,
        "date": "2026-04-26",
        "flow_m3s": 2707.9,
        "level_m": 21.937
      },
      {
        "day": 8,
        "date": "2026-04-27",
        "flow_m3s": 2686.1,
        "level_m": 21.764
      },
      {
        "day": 9,
        "date": "2026-04-28",
        "flow_m3s": 2602.0,
        "level_m": 21.774
      },
      {
        "day": 10,
        "date": "2026-04-29",
        "flow_m3s": 2502.0,
        "level_m": 21.71
      }
    ]
  },
  {
    "generated_at": "2026-04-20T20:02:04Z",
    "anchor_date": "2026-04-20",
    "forecast": [
      {
        "day": 1,
        "date": "2026-04-21",
        "flow_m3s": 2772.5,
        "level_m": 21.923
      },
      {
        "day": 2,
        "date": "2026-04-22",
        "flow_m3s": 2927.7,
        "level_m": 22.12
      },
      {
        "day": 3,
        "date": "2026-04-23",
        "flow_m3s": 2722.8,
        "level_m": 21.825
      },
      {
        "day": 4,
        "date": "2026-04-24",
        "flow_m3s": 2919.0,
        "level_m": 22.118
      },
      {
        "day": 5,
        "date": "2026-04-25",
        "flow_m3s": 2786.4,
        "level_m": 22.009
      },
      {
        "day": 6,
        "date": "2026-04-26",
        "flow_m3s": 2684.1,
        "level_m": 21.839
      },
      {
        "day": 7,
        "date": "2026-04-27",
        "flow_m3s": 2666.0,
        "level_m": 21.811
      },
      {
        "day": 8,
        "date": "2026-04-28",
        "flow_m3s": 2638.2,
        "level_m": 21.701
      },
      {
        "day": 9,
        "date": "2026-04-29",
        "flow_m3s": 2602.1,
        "level_m": 21.643
      },
      {
        "day": 10,
        "date": "2026-04-30",
        "flow_m3s": 2483.7,
        "level_m": 21.635
      }
    ]
  },
  {
    "generated_at": "2026-04-21T20:02:03Z",
    "anchor_date": "2026-04-21",
    "forecast": [
      {
        "day": 1,
        "date": "2026-04-22",
        "flow_m3s": 2788.3,
        "level_m": 21.984
      },
      {
        "day": 2,
        "date": "2026-04-23",
        "flow_m3s": 2949.9,
        "level_m": 22.177
      },
      {
        "day": 3,
        "date": "2026-04-24",
        "flow_m3s": 2666.2,
        "level_m": 21.777
      },
      {
        "day": 4,
        "date": "2026-04-25",
        "flow_m3s": 2836.1,
        "level_m": 21.933
      },
      {
        "day": 5,
        "date": "2026-04-26",
        "flow_m3s": 2709.5,
        "level_m": 21.909
      },
      {
        "day": 6,
        "date": "2026-04-27",
        "flow_m3s": 2612.1,
        "level_m": 21.819
      },
      {
        "day": 7,
        "date": "2026-04-28",
        "flow_m3s": 2585.5,
        "level_m": 21.816
      },
      {
        "day": 8,
        "date": "2026-04-29",
        "flow_m3s": 2631.2,
        "level_m": 21.579
      },
      {
        "day": 9,
        "date": "2026-04-30",
        "flow_m3s": 2524.4,
        "level_m": 21.697
      },
      {
        "day": 10,
        "date": "2026-05-01",
        "flow_m3s": 2422.3,
        "level_m": 21.688
      }
    ]
  },
  {
    "generated_at": "2026-04-22T20:01:27Z",
    "anchor_date": "2026-04-22",
    "forecast": [
      {
        "day": 1,
        "date": "2026-04-23",
        "flow_m3s": 2887.4,
        "level_m": 22.102
      },
      {
        "day": 2,
        "date": "2026-04-24",
        "flow_m3s": 2954.0,
        "level_m": 22.17
      },
      {
        "day": 3,
        "date": "2026-04-25",
        "flow_m3s": 2746.1,
        "level_m": 21.92
      },
      {
        "day": 4,
        "date": "2026-04-26",
        "flow_m3s": 2818.6,
        "level_m": 21.879
      },
      {
        "day": 5,
        "date": "2026-04-27",
        "flow_m3s": 2687.3,
        "level_m": 21.901
      },
      {
        "day": 6,
        "date": "2026-04-28",
        "flow_m3s": 2618.8,
        "level_m": 21.857
      },
      {
        "day": 7,
        "date": "2026-04-29",
        "flow_m3s": 2596.4,
        "level_m": 21.775
      },
      {
        "day": 8,
        "date": "2026-04-30",
        "flow_m3s": 2585.0,
        "level_m": 21.555
      },
      {
        "day": 9,
        "date": "2026-05-01",
        "flow_m3s": 2537.2,
        "level_m": 21.611
      },
      {
        "day": 10,
        "date": "2026-05-02",
        "flow_m3s": 2427.1,
        "level_m": 21.628
      }
    ]
  },
  {
    "generated_at": "2026-04-23T20:01:14Z",
    "anchor_date": "2026-04-23",
    "forecast": [
      {
        "day": 1,
        "date": "2026-04-24",
        "flow_m3s": 2944.7,
        "level_m": 22.13
      },
      {
        "day": 2,
        "date": "2026-04-25",
        "flow_m3s": 2962.9,
        "level_m": 22.188
      },
      {
        "day": 3,
        "date": "2026-04-26",
        "flow_m3s": 2739.2,
        "level_m": 21.975
      },
      {
        "day": 4,
        "date": "2026-04-27",
        "flow_m3s": 2825.9,
        "level_m": 21.885
      },
      {
        "day": 5,
        "date": "2026-04-28",
        "flow_m3s": 2683.9,
        "level_m": 21.879
      },
      {
        "day": 6,
        "date": "2026-04-29",
        "flow_m3s": 2620.1,
        "level_m": 21.851
      },
      {
        "day": 7,
        "date": "2026-04-30",
        "flow_m3s": 2593.4,
        "level_m": 21.792
      },
      {
        "day": 8,
        "date": "2026-05-01",
        "flow_m3s": 2575.7,
        "level_m": 21.543
      },
      {
        "day": 9,
        "date": "2026-05-02",
        "flow_m3s": 2482.5,
        "level_m": 21.629
      },
      {
        "day": 10,
        "date": "2026-05-03",
        "flow_m3s": 2417.9,
        "level_m": 21.686
      }
    ]
  },
  {
    "generated_at": "2026-04-24T11:01:51Z",
    "anchor_date": "2026-04-24",
    "forecast": [
      {
        "day": 1,
        "date": "2026-04-25",
        "flow_m3s": 2878.3,
        "level_m": 22.06
      },
      {
        "day": 2,
        "date": "2026-04-26",
        "flow_m3s": 2961.6,
        "level_m": 22.187
      },
      {
        "day": 3,
        "date": "2026-04-27",
        "flow_m3s": 2692.5,
        "level_m": 21.876
      },
      {
        "day": 4,
        "date": "2026-04-28",
        "flow_m3s": 2816.0,
        "level_m": 21.935
      },
      {
        "day": 5,
        "date": "2026-04-29",
        "flow_m3s": 2712.6,
        "level_m": 21.907
      },
      {
        "day": 6,
        "date": "2026-04-30",
        "flow_m3s": 2637.7,
        "level_m": 21.885
      },
      {
        "day": 7,
        "date": "2026-05-01",
        "flow_m3s": 2649.0,
        "level_m": 21.815
      },
      {
        "day": 8,
        "date": "2026-05-02",
        "flow_m3s": 2594.1,
        "level_m": 21.629
      },
      {
        "day": 9,
        "date": "2026-05-03",
        "flow_m3s": 2499.2,
        "level_m": 21.716
      },
      {
        "day": 10,
        "date": "2026-05-04",
        "flow_m3s": 2413.8,
        "level_m": 21.653
      }
    ]
  },
  {
    "generated_at": "2026-04-25T20:01:27Z",
    "anchor_date": "2026-04-25",
    "forecast": [
      {
        "day": 1,
        "date": "2026-04-26",
        "flow_m3s": 2765.8,
        "level_m": 21.915
      },
      {
        "day": 2,
        "date": "2026-04-27",
        "flow_m3s": 2907.9,
        "level_m": 22.131
      },
      {
        "day": 3,
        "date": "2026-04-28",
        "flow_m3s": 2621.5,
        "level_m": 21.782
      },
      {
        "day": 4,
        "date": "2026-04-29",
        "flow_m3s": 2801.4,
        "level_m": 21.946
      },
      {
        "day": 5,
        "date": "2026-04-30",
        "flow_m3s": 2787.1,
        "level_m": 21.895
      },
      {
        "day": 6,
        "date": "2026-05-01",
        "flow_m3s": 2762.1,
        "level_m": 21.981
      },
      {
        "day": 7,
        "date": "2026-05-02",
        "flow_m3s": 2734.4,
        "level_m": 22.002
      },
      {
        "day": 8,
        "date": "2026-05-03",
        "flow_m3s": 2723.4,
        "level_m": 21.858
      },
      {
        "day": 9,
        "date": "2026-05-04",
        "flow_m3s": 2672.2,
        "level_m": 21.933
      },
      {
        "day": 10,
        "date": "2026-05-05",
        "flow_m3s": 2626.9,
        "level_m": 21.892
      }
    ]
  },
  {
    "generated_at": "2026-04-26T20:01:03Z",
    "anchor_date": "2026-04-26",
    "forecast": [
      {
        "day": 1,
        "date": "2026-04-27",
        "flow_m3s": 2712.6,
        "level_m": 21.844
      },
      {
        "day": 2,
        "date": "2026-04-28",
        "flow_m3s": 2729.4,
        "level_m": 21.889
      },
      {
        "day": 3,
        "date": "2026-04-29",
        "flow_m3s": 2634.0,
        "level_m": 21.797
      },
      {
        "day": 4,
        "date": "2026-04-30",
        "flow_m3s": 2707.6,
        "level_m": 21.95
      },
      {
        "day": 5,
        "date": "2026-05-01",
        "flow_m3s": 2819.5,
        "level_m": 21.905
      },
      {
        "day": 6,
        "date": "2026-05-02",
        "flow_m3s": 2751.6,
        "level_m": 21.993
      },
      {
        "day": 7,
        "date": "2026-05-03",
        "flow_m3s": 2688.1,
        "level_m": 22.0
      },
      {
        "day": 8,
        "date": "2026-05-04",
        "flow_m3s": 2704.0,
        "level_m": 21.843
      },
      {
        "day": 9,
        "date": "2026-05-05",
        "flow_m3s": 2630.6,
        "level_m": 21.88
      },
      {
        "day": 10,
        "date": "2026-05-06",
        "flow_m3s": 2580.4,
        "level_m": 21.861
      }
    ]
  },
  {
    "generated_at": "2026-04-27T20:01:21Z",
    "anchor_date": "2026-04-27",
    "forecast": [
      {
        "day": 1,
        "date": "2026-04-28",
        "flow_m3s": 2705.9,
        "level_m": 21.793
      },
      {
        "day": 2,
        "date": "2026-04-29",
        "flow_m3s": 2696.0,
        "level_m": 21.855
      },
      {
        "day": 3,
        "date": "2026-04-30",
        "flow_m3s": 2647.6,
        "level_m": 21.77
      },
      {
        "day": 4,
        "date": "2026-05-01",
        "flow_m3s": 2685.5,
        "level_m": 22.011
      },
      {
        "day": 5,
        "date": "2026-05-02",
        "flow_m3s": 2773.3,
        "level_m": 21.805
      },
      {
        "day": 6,
        "date": "2026-05-03",
        "flow_m3s": 2618.8,
        "level_m": 21.866
      },
      {
        "day": 7,
        "date": "2026-05-04",
        "flow_m3s": 2625.0,
        "level_m": 21.827
      },
      {
        "day": 8,
        "date": "2026-05-05",
        "flow_m3s": 2587.5,
        "level_m": 21.614
      },
      {
        "day": 9,
        "date": "2026-05-06",
        "flow_m3s": 2406.1,
        "level_m": 21.65
      },
      {
        "day": 10,
        "date": "2026-05-07",
        "flow_m3s": 2362.0,
        "level_m": 21.67
      }
    ]
  },
  {
    "generated_at": "2026-04-28T20:01:25Z",
    "anchor_date": "2026-04-28",
    "forecast": [
      {
        "day": 1,
        "date": "2026-04-29",
        "flow_m3s": 2645.4,
        "level_m": 21.741
      },
      {
        "day": 2,
        "date": "2026-04-30",
        "flow_m3s": 2652.4,
        "level_m": 21.814
      },
      {
        "day": 3,
        "date": "2026-05-01",
        "flow_m3s": 2634.0,
        "level_m": 21.789
      },
      {
        "day": 4,
        "date": "2026-05-02",
        "flow_m3s": 2735.7,
        "level_m": 22.137
      },
      {
        "day": 5,
        "date": "2026-05-03",
        "flow_m3s": 2821.7,
        "level_m": 21.831
      },
      {
        "day": 6,
        "date": "2026-05-04",
        "flow_m3s": 2722.9,
        "level_m": 21.962
      },
      {
        "day": 7,
        "date": "2026-05-05",
        "flow_m3s": 2746.0,
        "level_m": 21.98
      },
      {
        "day": 8,
        "date": "2026-05-06",
        "flow_m3s": 2659.8,
        "level_m": 21.721
      },
      {
        "day": 9,
        "date": "2026-05-07",
        "flow_m3s": 2597.0,
        "level_m": 21.79
      },
      {
        "day": 10,
        "date": "2026-05-08",
        "flow_m3s": 2447.1,
        "level_m": 21.735
      }
    ]
  },
  {
    "generated_at": "2026-04-29T20:01:04Z",
    "anchor_date": "2026-04-29",
    "forecast": [
      {
        "day": 1,
        "date": "2026-04-30",
        "flow_m3s": 2659.1,
        "level_m": 21.761
      },
      {
        "day": 2,
        "date": "2026-05-01",
        "flow_m3s": 2667.1,
        "level_m": 21.829
      },
      {
        "day": 3,
        "date": "2026-05-02",
        "flow_m3s": 2637.5,
        "level_m": 21.804
      },
      {
        "day": 4,
        "date": "2026-05-03",
        "flow_m3s": 2696.5,
        "level_m": 22.117
      },
      {
        "day": 5,
        "date": "2026-05-04",
        "flow_m3s": 2805.8,
        "level_m": 21.756
      },
      {
        "day": 6,
        "date": "2026-05-05",
        "flow_m3s": 2691.7,
        "level_m": 21.885
      },
      {
        "day": 7,
        "date": "2026-05-06",
        "flow_m3s": 2715.8,
        "level_m": 21.938
      },
      {
        "day": 8,
        "date": "2026-05-07",
        "flow_m3s": 2646.8,
        "level_m": 21.741
      },
      {
        "day": 9,
        "date": "2026-05-08",
        "flow_m3s": 2524.9,
        "level_m": 21.767
      },
      {
        "day": 10,
        "date": "2026-05-09",
        "flow_m3s": 2447.7,
        "level_m": 21.796
      }
    ]
  },
  {
    "generated_at": "2026-04-30T20:01:29Z",
    "anchor_date": "2026-04-30",
    "forecast": [
      {
        "day": 1,
        "date": "2026-05-01",
        "flow_m3s": 2663.2,
        "level_m": 21.761
      },
      {
        "day": 2,
        "date": "2026-05-02",
        "flow_m3s": 2670.7,
        "level_m": 21.827
      },
      {
        "day": 3,
        "date": "2026-05-03",
        "flow_m3s": 2617.7,
        "level_m": 21.802
      },
      {
        "day": 4,
        "date": "2026-05-04",
        "flow_m3s": 2681.4,
        "level_m": 22.066
      },
      {
        "day": 5,
        "date": "2026-05-05",
        "flow_m3s": 2775.4,
        "level_m": 21.695
      },
      {
        "day": 6,
        "date": "2026-05-06",
        "flow_m3s": 2705.8,
        "level_m": 21.832
      },
      {
        "day": 7,
        "date": "2026-05-07",
        "flow_m3s": 2629.9,
        "level_m": 21.849
      },
      {
        "day": 8,
        "date": "2026-05-08",
        "flow_m3s": 2590.6,
        "level_m": 21.688
      },
      {
        "day": 9,
        "date": "2026-05-09",
        "flow_m3s": 2501.4,
        "level_m": 21.665
      },
      {
        "day": 10,
        "date": "2026-05-10",
        "flow_m3s": 2415.3,
        "level_m": 21.689
      }
    ]
  },
  {
    "generated_at": "2026-05-01T20:01:45Z",
    "anchor_date": "2026-05-01",
    "forecast": [
      {
        "day": 1,
        "date": "2026-05-02",
        "flow_m3s": 2658.3,
        "level_m": 21.838
      },
      {
        "day": 2,
        "date": "2026-05-03",
        "flow_m3s": 2645.4,
        "level_m": 21.803
      },
      {
        "day": 3,
        "date": "2026-05-04",
        "flow_m3s": 2599.7,
        "level_m": 21.738
      },
      {
        "day": 4,
        "date": "2026-05-05",
        "flow_m3s": 2676.3,
        "level_m": 22.055
      },
      {
        "day": 5,
        "date": "2026-05-06",
        "flow_m3s": 2766.3,
        "level_m": 21.766
      },
      {
        "day": 6,
        "date": "2026-05-07",
        "flow_m3s": 2693.9,
        "level_m": 21.835
      },
      {
        "day": 7,
        "date": "2026-05-08",
        "flow_m3s": 2671.1,
        "level_m": 21.833
      },
      {
        "day": 8,
        "date": "2026-05-09",
        "flow_m3s": 2558.3,
        "level_m": 21.693
      },
      {
        "day": 9,
        "date": "2026-05-10",
        "flow_m3s": 2504.8,
        "level_m": 21.66
      },
      {
        "day": 10,
        "date": "2026-05-11",
        "flow_m3s": 2398.1,
        "level_m": 21.679
      }
    ]
  },
  {
    "generated_at": "2026-05-02T20:01:35Z",
    "anchor_date": "2026-05-02",
    "forecast": [
      {
        "day": 1,
        "date": "2026-05-03",
        "flow_m3s": 2697.7,
        "level_m": 21.824
      },
      {
        "day": 2,
        "date": "2026-05-04",
        "flow_m3s": 2668.6,
        "level_m": 21.837
      },
      {
        "day": 3,
        "date": "2026-05-05",
        "flow_m3s": 2615.5,
        "level_m": 21.736
      },
      {
        "day": 4,
        "date": "2026-05-06",
        "flow_m3s": 2680.9,
        "level_m": 22.049
      },
      {
        "day": 5,
        "date": "2026-05-07",
        "flow_m3s": 2774.7,
        "level_m": 21.757
      },
      {
        "day": 6,
        "date": "2026-05-08",
        "flow_m3s": 2676.7,
        "level_m": 21.894
      },
      {
        "day": 7,
        "date": "2026-05-09",
        "flow_m3s": 2648.5,
        "level_m": 21.921
      },
      {
        "day": 8,
        "date": "2026-05-10",
        "flow_m3s": 2590.4,
        "level_m": 21.68
      },
      {
        "day": 9,
        "date": "2026-05-11",
        "flow_m3s": 2534.0,
        "level_m": 21.674
      },
      {
        "day": 10,
        "date": "2026-05-12",
        "flow_m3s": 2389.2,
        "level_m": 21.673
      }
    ]
  },
  {
    "generated_at": "2026-05-03T20:01:18Z",
    "anchor_date": "2026-05-03",
    "forecast": [
      {
        "day": 1,
        "date": "2026-05-04",
        "flow_m3s": 2690.6,
        "level_m": 21.8
      },
      {
        "day": 2,
        "date": "2026-05-05",
        "flow_m3s": 2628.3,
        "level_m": 21.812
      },
      {
        "day": 3,
        "date": "2026-05-06",
        "flow_m3s": 2593.9,
        "level_m": 21.705
      },
      {
        "day": 4,
        "date": "2026-05-07",
        "flow_m3s": 2594.6,
        "level_m": 21.889
      },
      {
        "day": 5,
        "date": "2026-05-08",
        "flow_m3s": 2626.7,
        "level_m": 21.655
      },
      {
        "day": 6,
        "date": "2026-05-09",
        "flow_m3s": 2584.5,
        "level_m": 21.773
      },
      {
        "day": 7,
        "date": "2026-05-10",
        "flow_m3s": 2570.0,
        "level_m": 21.749
      },
      {
        "day": 8,
        "date": "2026-05-11",
        "flow_m3s": 2532.0,
        "level_m": 21.542
      },
      {
        "day": 9,
        "date": "2026-05-12",
        "flow_m3s": 2446.4,
        "level_m": 21.589
      },
      {
        "day": 10,
        "date": "2026-05-13",
        "flow_m3s": 2323.9,
        "level_m": 21.61
      }
    ]
  },
  {
    "generated_at": "2026-05-04T20:01:26Z",
    "anchor_date": "2026-05-04",
    "forecast": [
      {
        "day": 1,
        "date": "2026-05-05",
        "flow_m3s": 2623.9,
        "level_m": 21.739
      },
      {
        "day": 2,
        "date": "2026-05-06",
        "flow_m3s": 2580.2,
        "level_m": 21.748
      },
      {
        "day": 3,
        "date": "2026-05-07",
        "flow_m3s": 2598.0,
        "level_m": 21.71
      },
      {
        "day": 4,
        "date": "2026-05-08",
        "flow_m3s": 2568.6,
        "level_m": 21.899
      },
      {
        "day": 5,
        "date": "2026-05-09",
        "flow_m3s": 2640.8,
        "level_m": 21.619
      },
      {
        "day": 6,
        "date": "2026-05-10",
        "flow_m3s": 2599.6,
        "level_m": 21.767
      },
      {
        "day": 7,
        "date": "2026-05-11",
        "flow_m3s": 2594.0,
        "level_m": 21.749
      },
      {
        "day": 8,
        "date": "2026-05-12",
        "flow_m3s": 2517.3,
        "level_m": 21.525
      },
      {
        "day": 9,
        "date": "2026-05-13",
        "flow_m3s": 2439.4,
        "level_m": 21.548
      },
      {
        "day": 10,
        "date": "2026-05-14",
        "flow_m3s": 2322.2,
        "level_m": 21.593
      }
    ]
  },
  {
    "generated_at": "2026-05-05T20:01:44Z",
    "anchor_date": "2026-05-05",
    "forecast": [
      {
        "day": 1,
        "date": "2026-05-06",
        "flow_m3s": 2634.2,
        "level_m": 21.695
      },
      {
        "day": 2,
        "date": "2026-05-07",
        "flow_m3s": 2574.0,
        "level_m": 21.693
      },
      {
        "day": 3,
        "date": "2026-05-08",
        "flow_m3s": 2595.4,
        "level_m": 21.644
      },
      {
        "day": 4,
        "date": "2026-05-09",
        "flow_m3s": 2601.6,
        "level_m": 21.92
      },
      {
        "day": 5,
        "date": "2026-05-10",
        "flow_m3s": 2664.2,
        "level_m": 21.637
      },
      {
        "day": 6,
        "date": "2026-05-11",
        "flow_m3s": 2623.4,
        "level_m": 21.771
      },
      {
        "day": 7,
        "date": "2026-05-12",
        "flow_m3s": 2599.1,
        "level_m": 21.783
      },
      {
        "day": 8,
        "date": "2026-05-13",
        "flow_m3s": 2495.4,
        "level_m": 21.513
      },
      {
        "day": 9,
        "date": "2026-05-14",
        "flow_m3s": 2352.2,
        "level_m": 21.578
      },
      {
        "day": 10,
        "date": "2026-05-15",
        "flow_m3s": 2288.2,
        "level_m": 21.554
      }
    ]
  },
  {
    "generated_at": "2026-05-06T20:01:38Z",
    "anchor_date": "2026-05-06",
    "forecast": [
      {
        "day": 1,
        "date": "2026-05-07",
        "flow_m3s": 2533.7,
        "level_m": 21.629
      },
      {
        "day": 2,
        "date": "2026-05-08",
        "flow_m3s": 2495.2,
        "level_m": 21.608
      },
      {
        "day": 3,
        "date": "2026-05-09",
        "flow_m3s": 2503.8,
        "level_m": 21.615
      },
      {
        "day": 4,
        "date": "2026-05-10",
        "flow_m3s": 2556.9,
        "level_m": 21.852
      },
      {
        "day": 5,
        "date": "2026-05-11",
        "flow_m3s": 2728.5,
        "level_m": 21.624
      },
      {
        "day": 6,
        "date": "2026-05-12",
        "flow_m3s": 2617.7,
        "level_m": 21.781
      },
      {
        "day": 7,
        "date": "2026-05-13",
        "flow_m3s": 2584.8,
        "level_m": 21.771
      },
      {
        "day": 8,
        "date": "2026-05-14",
        "flow_m3s": 2469.8,
        "level_m": 21.505
      },
      {
        "day": 9,
        "date": "2026-05-15",
        "flow_m3s": 2339.4,
        "level_m": 21.571
      },
      {
        "day": 10,
        "date": "2026-05-16",
        "flow_m3s": 2285.4,
        "level_m": 21.511
      }
    ]
  },
  {
    "generated_at": "2026-05-07T20:01:22Z",
    "anchor_date": "2026-05-07",
    "forecast": [
      {
        "day": 1,
        "date": "2026-05-08",
        "flow_m3s": 2480.5,
        "level_m": 21.576
      },
      {
        "day": 2,
        "date": "2026-05-09",
        "flow_m3s": 2473.8,
        "level_m": 21.538
      },
      {
        "day": 3,
        "date": "2026-05-10",
        "flow_m3s": 2495.6,
        "level_m": 21.54
      },
      {
        "day": 4,
        "date": "2026-05-11",
        "flow_m3s": 2562.3,
        "level_m": 21.802
      },
      {
        "day": 5,
        "date": "2026-05-12",
        "flow_m3s": 2707.8,
        "level_m": 21.595
      },
      {
        "day": 6,
        "date": "2026-05-13",
        "flow_m3s": 2621.3,
        "level_m": 21.779
      },
      {
        "day": 7,
        "date": "2026-05-14",
        "flow_m3s": 2557.0,
        "level_m": 21.781
      },
      {
        "day": 8,
        "date": "2026-05-15",
        "flow_m3s": 2462.5,
        "level_m": 21.471
      },
      {
        "day": 9,
        "date": "2026-05-16",
        "flow_m3s": 2320.4,
        "level_m": 21.546
      },
      {
        "day": 10,
        "date": "2026-05-17",
        "flow_m3s": 2296.0,
        "level_m": 21.518
      }
    ]
  },
  {
    "generated_at": "2026-05-08T20:01:14Z",
    "anchor_date": "2026-05-08",
    "forecast": [
      {
        "day": 1,
        "date": "2026-05-09",
        "flow_m3s": 2351.6,
        "level_m": 21.429
      },
      {
        "day": 2,
        "date": "2026-05-10",
        "flow_m3s": 2371.0,
        "level_m": 21.434
      },
      {
        "day": 3,
        "date": "2026-05-11",
        "flow_m3s": 2467.7,
        "level_m": 21.45
      },
      {
        "day": 4,
        "date": "2026-05-12",
        "flow_m3s": 2383.1,
        "level_m": 21.513
      },
      {
        "day": 5,
        "date": "2026-05-13",
        "flow_m3s": 2501.1,
        "level_m": 21.437
      },
      {
        "day": 6,
        "date": "2026-05-14",
        "flow_m3s": 2349.1,
        "level_m": 21.483
      },
      {
        "day": 7,
        "date": "2026-05-15",
        "flow_m3s": 2359.9,
        "level_m": 21.522
      },
      {
        "day": 8,
        "date": "2026-05-16",
        "flow_m3s": 2287.0,
        "level_m": 21.343
      },
      {
        "day": 9,
        "date": "2026-05-17",
        "flow_m3s": 2187.1,
        "level_m": 21.3
      },
      {
        "day": 10,
        "date": "2026-05-18",
        "flow_m3s": 2062.2,
        "level_m": 21.224
      }
    ]
  },
  {
    "generated_at": "2026-05-09T20:01:22Z",
    "anchor_date": "2026-05-09",
    "forecast": [
      {
        "day": 1,
        "date": "2026-05-10",
        "flow_m3s": 2300.9,
        "level_m": 21.326
      },
      {
        "day": 2,
        "date": "2026-05-11",
        "flow_m3s": 2315.1,
        "level_m": 21.33
      },
      {
        "day": 3,
        "date": "2026-05-12",
        "flow_m3s": 2393.6,
        "level_m": 21.401
      },
      {
        "day": 4,
        "date": "2026-05-13",
        "flow_m3s": 2352.2,
        "level_m": 21.452
      },
      {
        "day": 5,
        "date": "2026-05-14",
        "flow_m3s": 2464.3,
        "level_m": 21.365
      },
      {
        "day": 6,
        "date": "2026-05-15",
        "flow_m3s": 2308.3,
        "level_m": 21.424
      },
      {
        "day": 7,
        "date": "2026-05-16",
        "flow_m3s": 2293.2,
        "level_m": 21.478
      },
      {
        "day": 8,
        "date": "2026-05-17",
        "flow_m3s": 2277.3,
        "level_m": 21.252
      },
      {
        "day": 9,
        "date": "2026-05-18",
        "flow_m3s": 2211.0,
        "level_m": 21.245
      },
      {
        "day": 10,
        "date": "2026-05-19",
        "flow_m3s": 2173.4,
        "level_m": 21.218
      }
    ]
  },
  {
    "generated_at": "2026-05-10T11:01:21Z",
    "anchor_date": "2026-05-10",
    "forecast": [
      {
        "day": 1,
        "date": "2026-05-11",
        "flow_m3s": 2245.5,
        "level_m": 21.274
      },
      {
        "day": 2,
        "date": "2026-05-12",
        "flow_m3s": 2269.1,
        "level_m": 21.302
      },
      {
        "day": 3,
        "date": "2026-05-13",
        "flow_m3s": 2257.7,
        "level_m": 21.265
      },
      {
        "day": 4,
        "date": "2026-05-14",
        "flow_m3s": 2235.8,
        "level_m": 21.363
      },
      {
        "day": 5,
        "date": "2026-05-15",
        "flow_m3s": 2352.0,
        "level_m": 21.309
      },
      {
        "day": 6,
        "date": "2026-05-16",
        "flow_m3s": 2240.4,
        "level_m": 21.396
      },
      {
        "day": 7,
        "date": "2026-05-17",
        "flow_m3s": 2206.9,
        "level_m": 21.404
      },
      {
        "day": 8,
        "date": "2026-05-18",
        "flow_m3s": 2174.6,
        "level_m": 21.176
      },
      {
        "day": 9,
        "date": "2026-05-19",
        "flow_m3s": 2218.7,
        "level_m": 21.188
      },
      {
        "day": 10,
        "date": "2026-05-20",
        "flow_m3s": 2205.3,
        "level_m": 21.21
      }
    ]
  },
  {
    "generated_at": "2026-05-25T00:39:41Z",
    "anchor_date": "2026-05-24",
    "forecast": [
      {
        "day": 1,
        "date": "2026-05-25",
        "flow_m3s": 1797.4,
        "level_m": 20.735
      },
      {
        "day": 2,
        "date": "2026-05-26",
        "flow_m3s": 1742.1,
        "level_m": 20.719
      },
      {
        "day": 3,
        "date": "2026-05-27",
        "flow_m3s": 1730.7,
        "level_m": 20.716
      },
      {
        "day": 4,
        "date": "2026-05-28",
        "flow_m3s": 1725.3,
        "level_m": 20.649
      },
      {
        "day": 5,
        "date": "2026-05-29",
        "flow_m3s": 1652.1,
        "level_m": 20.685
      },
      {
        "day": 6,
        "date": "2026-05-30",
        "flow_m3s": 1747.0,
        "level_m": 20.698
      },
      {
        "day": 7,
        "date": "2026-05-31",
        "flow_m3s": 1706.3,
        "level_m": 20.717
      },
      {
        "day": 8,
        "date": "2026-06-01",
        "flow_m3s": 1592.6,
        "level_m": 20.623
      },
      {
        "day": 9,
        "date": "2026-06-02",
        "flow_m3s": 1554.5,
        "level_m": 20.488
      },
      {
        "day": 10,
        "date": "2026-06-03",
        "flow_m3s": 1584.2,
        "level_m": 20.388
      }
    ]
  },
  {
    "generated_at": "2026-05-25T20:01:47Z",
    "anchor_date": "2026-05-25",
    "forecast": [
      {
        "day": 1,
        "date": "2026-05-26",
        "flow_m3s": 1848.2,
        "level_m": 20.794
      },
      {
        "day": 2,
        "date": "2026-05-27",
        "flow_m3s": 1818.0,
        "level_m": 20.773
      },
      {
        "day": 3,
        "date": "2026-05-28",
        "flow_m3s": 1771.6,
        "level_m": 20.681
      },
      {
        "day": 4,
        "date": "2026-05-29",
        "flow_m3s": 1724.4,
        "level_m": 20.675
      },
      {
        "day": 5,
        "date": "2026-05-30",
        "flow_m3s": 1669.2,
        "level_m": 20.637
      },
      {
        "day": 6,
        "date": "2026-05-31",
        "flow_m3s": 1761.5,
        "level_m": 20.642
      },
      {
        "day": 7,
        "date": "2026-06-01",
        "flow_m3s": 1734.3,
        "level_m": 20.722
      },
      {
        "day": 8,
        "date": "2026-06-02",
        "flow_m3s": 1679.3,
        "level_m": 20.578
      },
      {
        "day": 9,
        "date": "2026-06-03",
        "flow_m3s": 1649.4,
        "level_m": 20.476
      },
      {
        "day": 10,
        "date": "2026-06-04",
        "flow_m3s": 1612.8,
        "level_m": 20.433
      }
    ]
  },
  {
    "generated_at": "2026-05-26T20:01:59Z",
    "anchor_date": "2026-05-26",
    "forecast": [
      {
        "day": 1,
        "date": "2026-05-27",
        "flow_m3s": 1830.9,
        "level_m": 20.777
      },
      {
        "day": 2,
        "date": "2026-05-28",
        "flow_m3s": 1802.6,
        "level_m": 20.73
      },
      {
        "day": 3,
        "date": "2026-05-29",
        "flow_m3s": 1753.6,
        "level_m": 20.648
      },
      {
        "day": 4,
        "date": "2026-05-30",
        "flow_m3s": 1696.6,
        "level_m": 20.587
      },
      {
        "day": 5,
        "date": "2026-05-31",
        "flow_m3s": 1618.0,
        "level_m": 20.539
      },
      {
        "day": 6,
        "date": "2026-06-01",
        "flow_m3s": 1566.0,
        "level_m": 20.484
      },
      {
        "day": 7,
        "date": "2026-06-02",
        "flow_m3s": 1522.6,
        "level_m": 20.441
      },
      {
        "day": 8,
        "date": "2026-06-03",
        "flow_m3s": 1546.1,
        "level_m": 20.444
      },
      {
        "day": 9,
        "date": "2026-06-04",
        "flow_m3s": 1429.6,
        "level_m": 20.365
      },
      {
        "day": 10,
        "date": "2026-06-05",
        "flow_m3s": 1427.6,
        "level_m": 20.243
      }
    ]
  },
  {
    "generated_at": "2026-05-27T20:01:55Z",
    "anchor_date": "2026-05-27",
    "forecast": [
      {
        "day": 1,
        "date": "2026-05-28",
        "flow_m3s": 1745.6,
        "level_m": 20.673
      },
      {
        "day": 2,
        "date": "2026-05-29",
        "flow_m3s": 1709.6,
        "level_m": 20.649
      },
      {
        "day": 3,
        "date": "2026-05-30",
        "flow_m3s": 1691.0,
        "level_m": 20.585
      },
      {
        "day": 4,
        "date": "2026-05-31",
        "flow_m3s": 1620.3,
        "level_m": 20.48
      },
      {
        "day": 5,
        "date": "2026-06-01",
        "flow_m3s": 1543.0,
        "level_m": 20.413
      },
      {
        "day": 6,
        "date": "2026-06-02",
        "flow_m3s": 1504.1,
        "level_m": 20.366
      },
      {
        "day": 7,
        "date": "2026-06-03",
        "flow_m3s": 1420.8,
        "level_m": 20.316
      },
      {
        "day": 8,
        "date": "2026-06-04",
        "flow_m3s": 1402.5,
        "level_m": 20.317
      },
      {
        "day": 9,
        "date": "2026-06-05",
        "flow_m3s": 1369.3,
        "level_m": 20.227
      },
      {
        "day": 10,
        "date": "2026-06-06",
        "flow_m3s": 1370.3,
        "level_m": 20.167
      }
    ]
  },
  {
    "generated_at": "2026-05-28T20:01:38Z",
    "anchor_date": "2026-05-28",
    "forecast": [
      {
        "day": 1,
        "date": "2026-05-29",
        "flow_m3s": 1688.3,
        "level_m": 20.578
      },
      {
        "day": 2,
        "date": "2026-05-30",
        "flow_m3s": 1643.0,
        "level_m": 20.535
      },
      {
        "day": 3,
        "date": "2026-05-31",
        "flow_m3s": 1606.9,
        "level_m": 20.506
      },
      {
        "day": 4,
        "date": "2026-06-01",
        "flow_m3s": 1564.7,
        "level_m": 20.453
      },
      {
        "day": 5,
        "date": "2026-06-02",
        "flow_m3s": 1507.2,
        "level_m": 20.389
      },
      {
        "day": 6,
        "date": "2026-06-03",
        "flow_m3s": 1469.8,
        "level_m": 20.355
      },
      {
        "day": 7,
        "date": "2026-06-04",
        "flow_m3s": 1398.3,
        "level_m": 20.328
      },
      {
        "day": 8,
        "date": "2026-06-05",
        "flow_m3s": 1408.2,
        "level_m": 20.318
      },
      {
        "day": 9,
        "date": "2026-06-06",
        "flow_m3s": 1402.9,
        "level_m": 20.252
      },
      {
        "day": 10,
        "date": "2026-06-07",
        "flow_m3s": 1380.1,
        "level_m": 20.214
      }
    ]
  },
  {
    "generated_at": "2026-05-29T20:01:54Z",
    "anchor_date": "2026-05-29",
    "forecast": [
      {
        "day": 1,
        "date": "2026-05-30",
        "flow_m3s": 1586.0,
        "level_m": 20.439
      },
      {
        "day": 2,
        "date": "2026-05-31",
        "flow_m3s": 1538.2,
        "level_m": 20.415
      },
      {
        "day": 3,
        "date": "2026-06-01",
        "flow_m3s": 1571.8,
        "level_m": 20.371
      },
      {
        "day": 4,
        "date": "2026-06-02",
        "flow_m3s": 1468.5,
        "level_m": 20.29
      },
      {
        "day": 5,
        "date": "2026-06-03",
        "flow_m3s": 1441.6,
        "level_m": 20.275
      },
      {
        "day": 6,
        "date": "2026-06-04",
        "flow_m3s": 1403.8,
        "level_m": 20.223
      },
      {
        "day": 7,
        "date": "2026-06-05",
        "flow_m3s": 1341.4,
        "level_m": 20.226
      },
      {
        "day": 8,
        "date": "2026-06-06",
        "flow_m3s": 1362.2,
        "level_m": 20.202
      },
      {
        "day": 9,
        "date": "2026-06-07",
        "flow_m3s": 1338.6,
        "level_m": 20.139
      },
      {
        "day": 10,
        "date": "2026-06-08",
        "flow_m3s": 1281.9,
        "level_m": 20.095
      }
    ]
  },
  {
    "generated_at": "2026-05-30T20:01:25Z",
    "anchor_date": "2026-05-30",
    "forecast": [
      {
        "day": 1,
        "date": "2026-05-31",
        "flow_m3s": 1480.6,
        "level_m": 20.341
      },
      {
        "day": 2,
        "date": "2026-06-01",
        "flow_m3s": 1435.4,
        "level_m": 20.297
      },
      {
        "day": 3,
        "date": "2026-06-02",
        "flow_m3s": 1441.5,
        "level_m": 20.265
      },
      {
        "day": 4,
        "date": "2026-06-03",
        "flow_m3s": 1356.9,
        "level_m": 20.175
      },
      {
        "day": 5,
        "date": "2026-06-04",
        "flow_m3s": 1359.9,
        "level_m": 20.202
      },
      {
        "day": 6,
        "date": "2026-06-05",
        "flow_m3s": 1289.8,
        "level_m": 20.197
      },
      {
        "day": 7,
        "date": "2026-06-06",
        "flow_m3s": 1270.2,
        "level_m": 20.129
      },
      {
        "day": 8,
        "date": "2026-06-07",
        "flow_m3s": 1252.7,
        "level_m": 20.084
      },
      {
        "day": 9,
        "date": "2026-06-08",
        "flow_m3s": 1274.6,
        "level_m": 20.022
      },
      {
        "day": 10,
        "date": "2026-06-09",
        "flow_m3s": 1193.3,
        "level_m": 19.991
      }
    ]
  },
  {
    "generated_at": "2026-05-31T20:01:30Z",
    "anchor_date": "2026-05-31",
    "forecast": [
      {
        "day": 1,
        "date": "2026-06-01",
        "flow_m3s": 1475.4,
        "level_m": 20.336
      },
      {
        "day": 2,
        "date": "2026-06-02",
        "flow_m3s": 1426.7,
        "level_m": 20.299
      },
      {
        "day": 3,
        "date": "2026-06-03",
        "flow_m3s": 1414.8,
        "level_m": 20.255
      },
      {
        "day": 4,
        "date": "2026-06-04",
        "flow_m3s": 1368.9,
        "level_m": 20.197
      },
      {
        "day": 5,
        "date": "2026-06-05",
        "flow_m3s": 1372.7,
        "level_m": 20.228
      },
      {
        "day": 6,
        "date": "2026-06-06",
        "flow_m3s": 1299.5,
        "level_m": 20.214
      },
      {
        "day": 7,
        "date": "2026-06-07",
        "flow_m3s": 1260.6,
        "level_m": 20.129
      },
      {
        "day": 8,
        "date": "2026-06-08",
        "flow_m3s": 1268.5,
        "level_m": 20.104
      },
      {
        "day": 9,
        "date": "2026-06-09",
        "flow_m3s": 1244.1,
        "level_m": 20.107
      },
      {
        "day": 10,
        "date": "2026-06-10",
        "flow_m3s": 1155.1,
        "level_m": 20.012
      }
    ]
  },
  {
    "generated_at": "2026-06-01T20:02:10Z",
    "anchor_date": "2026-06-01",
    "forecast": [
      {
        "day": 1,
        "date": "2026-06-02",
        "flow_m3s": 1709.3,
        "level_m": 20.55
      },
      {
        "day": 2,
        "date": "2026-06-03",
        "flow_m3s": 1573.9,
        "level_m": 20.513
      },
      {
        "day": 3,
        "date": "2026-06-04",
        "flow_m3s": 1492.8,
        "level_m": 20.418
      },
      {
        "day": 4,
        "date": "2026-06-05",
        "flow_m3s": 1467.1,
        "level_m": 20.403
      },
      {
        "day": 5,
        "date": "2026-06-06",
        "flow_m3s": 1477.3,
        "level_m": 20.29
      },
      {
        "day": 6,
        "date": "2026-06-07",
        "flow_m3s": 1410.0,
        "level_m": 20.271
      },
      {
        "day": 7,
        "date": "2026-06-08",
        "flow_m3s": 1453.4,
        "level_m": 20.257
      },
      {
        "day": 8,
        "date": "2026-06-09",
        "flow_m3s": 1332.0,
        "level_m": 20.149
      },
      {
        "day": 9,
        "date": "2026-06-10",
        "flow_m3s": 1305.1,
        "level_m": 20.077
      },
      {
        "day": 10,
        "date": "2026-06-11",
        "flow_m3s": 1231.7,
        "level_m": 20.084
      }
    ]
  },
  {
    "generated_at": "2026-06-02T20:01:35Z",
    "anchor_date": "2026-06-02",
    "forecast": [
      {
        "day": 1,
        "date": "2026-06-03",
        "flow_m3s": 1328.6,
        "level_m": 20.2
      },
      {
        "day": 2,
        "date": "2026-06-04",
        "flow_m3s": 1291.5,
        "level_m": 20.189
      },
      {
        "day": 3,
        "date": "2026-06-05",
        "flow_m3s": 1266.7,
        "level_m": 20.133
      },
      {
        "day": 4,
        "date": "2026-06-06",
        "flow_m3s": 1331.6,
        "level_m": 20.138
      },
      {
        "day": 5,
        "date": "2026-06-07",
        "flow_m3s": 1358.0,
        "level_m": 20.169
      },
      {
        "day": 6,
        "date": "2026-06-08",
        "flow_m3s": 1379.5,
        "level_m": 20.189
      },
      {
        "day": 7,
        "date": "2026-06-09",
        "flow_m3s": 1406.9,
        "level_m": 20.269
      },
      {
        "day": 8,
        "date": "2026-06-10",
        "flow_m3s": 1409.9,
        "level_m": 20.172
      },
      {
        "day": 9,
        "date": "2026-06-11",
        "flow_m3s": 1344.4,
        "level_m": 20.048
      },
      {
        "day": 10,
        "date": "2026-06-12",
        "flow_m3s": 1214.9,
        "level_m": 20.141
      }
    ]
  },
  {
    "generated_at": "2026-06-03T20:01:27Z",
    "anchor_date": "2026-06-03",
    "forecast": [
      {
        "day": 1,
        "date": "2026-06-04",
        "flow_m3s": 1303.5,
        "level_m": 20.161
      },
      {
        "day": 2,
        "date": "2026-06-05",
        "flow_m3s": 1285.2,
        "level_m": 20.152
      },
      {
        "day": 3,
        "date": "2026-06-06",
        "flow_m3s": 1280.9,
        "level_m": 20.162
      },
      {
        "day": 4,
        "date": "2026-06-07",
        "flow_m3s": 1341.4,
        "level_m": 20.154
      },
      {
        "day": 5,
        "date": "2026-06-08",
        "flow_m3s": 1287.5,
        "level_m": 20.108
      },
      {
        "day": 6,
        "date": "2026-06-09",
        "flow_m3s": 1222.9,
        "level_m": 20.007
      },
      {
        "day": 7,
        "date": "2026-06-10",
        "flow_m3s": 1186.8,
        "level_m": 20.031
      },
      {
        "day": 8,
        "date": "2026-06-11",
        "flow_m3s": 1165.0,
        "level_m": 19.956
      },
      {
        "day": 9,
        "date": "2026-06-12",
        "flow_m3s": 1144.4,
        "level_m": 19.966
      },
      {
        "day": 10,
        "date": "2026-06-13",
        "flow_m3s": 1103.7,
        "level_m": 19.88
      }
    ]
  },
  {
    "generated_at": "2026-06-04T20:01:56Z",
    "anchor_date": "2026-06-04",
    "forecast": [
      {
        "day": 1,
        "date": "2026-06-05",
        "flow_m3s": 1302.7,
        "level_m": 20.163
      },
      {
        "day": 2,
        "date": "2026-06-06",
        "flow_m3s": 1282.2,
        "level_m": 20.129
      },
      {
        "day": 3,
        "date": "2026-06-07",
        "flow_m3s": 1301.7,
        "level_m": 20.161
      },
      {
        "day": 4,
        "date": "2026-06-08",
        "flow_m3s": 1331.5,
        "level_m": 20.134
      },
      {
        "day": 5,
        "date": "2026-06-09",
        "flow_m3s": 1278.7,
        "level_m": 20.095
      },
      {
        "day": 6,
        "date": "2026-06-10",
        "flow_m3s": 1230.9,
        "level_m": 19.992
      },
      {
        "day": 7,
        "date": "2026-06-11",
        "flow_m3s": 1195.7,
        "level_m": 20.007
      },
      {
        "day": 8,
        "date": "2026-06-12",
        "flow_m3s": 1155.2,
        "level_m": 19.924
      },
      {
        "day": 9,
        "date": "2026-06-13",
        "flow_m3s": 1143.3,
        "level_m": 19.9
      },
      {
        "day": 10,
        "date": "2026-06-14",
        "flow_m3s": 1105.3,
        "level_m": 19.913
      }
    ]
  },
  {
    "generated_at": "2026-06-05T20:01:42Z",
    "anchor_date": "2026-06-05",
    "forecast": [
      {
        "day": 1,
        "date": "2026-06-06",
        "flow_m3s": 1263.2,
        "level_m": 20.099
      },
      {
        "day": 2,
        "date": "2026-06-07",
        "flow_m3s": 1291.6,
        "level_m": 20.153
      },
      {
        "day": 3,
        "date": "2026-06-08",
        "flow_m3s": 1272.9,
        "level_m": 20.132
      },
      {
        "day": 4,
        "date": "2026-06-09",
        "flow_m3s": 1262.0,
        "level_m": 20.097
      },
      {
        "day": 5,
        "date": "2026-06-10",
        "flow_m3s": 1250.0,
        "level_m": 20.057
      },
      {
        "day": 6,
        "date": "2026-06-11",
        "flow_m3s": 1207.0,
        "level_m": 19.972
      },
      {
        "day": 7,
        "date": "2026-06-12",
        "flow_m3s": 1162.2,
        "level_m": 19.972
      },
      {
        "day": 8,
        "date": "2026-06-13",
        "flow_m3s": 1105.3,
        "level_m": 19.883
      },
      {
        "day": 9,
        "date": "2026-06-14",
        "flow_m3s": 1133.9,
        "level_m": 19.842
      },
      {
        "day": 10,
        "date": "2026-06-15",
        "flow_m3s": 1096.7,
        "level_m": 19.844
      }
    ]
  },
  {
    "generated_at": "2026-06-06T20:02:04Z",
    "anchor_date": "2026-06-06",
    "forecast": [
      {
        "day": 1,
        "date": "2026-06-07",
        "flow_m3s": 1259.6,
        "level_m": 20.078
      },
      {
        "day": 2,
        "date": "2026-06-08",
        "flow_m3s": 1266.5,
        "level_m": 20.106
      },
      {
        "day": 3,
        "date": "2026-06-09",
        "flow_m3s": 1208.2,
        "level_m": 20.039
      },
      {
        "day": 4,
        "date": "2026-06-10",
        "flow_m3s": 1231.4,
        "level_m": 20.032
      },
      {
        "day": 5,
        "date": "2026-06-11",
        "flow_m3s": 1227.8,
        "level_m": 20.049
      },
      {
        "day": 6,
        "date": "2026-06-12",
        "flow_m3s": 1198.8,
        "level_m": 20.014
      },
      {
        "day": 7,
        "date": "2026-06-13",
        "flow_m3s": 1209.4,
        "level_m": 20.003
      },
      {
        "day": 8,
        "date": "2026-06-14",
        "flow_m3s": 1147.9,
        "level_m": 19.987
      },
      {
        "day": 9,
        "date": "2026-06-15",
        "flow_m3s": 1156.9,
        "level_m": 19.98
      },
      {
        "day": 10,
        "date": "2026-06-16",
        "flow_m3s": 1171.8,
        "level_m": 19.892
      }
    ]
  },
  {
    "generated_at": "2026-06-07T20:01:49Z",
    "anchor_date": "2026-06-07",
    "forecast": [
      {
        "day": 1,
        "date": "2026-06-08",
        "flow_m3s": 1265.6,
        "level_m": 20.029
      },
      {
        "day": 2,
        "date": "2026-06-09",
        "flow_m3s": 1220.8,
        "level_m": 20.044
      },
      {
        "day": 3,
        "date": "2026-06-10",
        "flow_m3s": 1217.8,
        "level_m": 20.041
      },
      {
        "day": 4,
        "date": "2026-06-11",
        "flow_m3s": 1234.9,
        "level_m": 20.083
      },
      {
        "day": 5,
        "date": "2026-06-12",
        "flow_m3s": 1234.6,
        "level_m": 20.059
      },
      {
        "day": 6,
        "date": "2026-06-13",
        "flow_m3s": 1256.4,
        "level_m": 20.037
      },
      {
        "day": 7,
        "date": "2026-06-14",
        "flow_m3s": 1207.1,
        "level_m": 20.004
      },
      {
        "day": 8,
        "date": "2026-06-15",
        "flow_m3s": 1131.2,
        "level_m": 19.961
      },
      {
        "day": 9,
        "date": "2026-06-16",
        "flow_m3s": 1147.1,
        "level_m": 19.928
      },
      {
        "day": 10,
        "date": "2026-06-17",
        "flow_m3s": 1134.2,
        "level_m": 19.913
      }
    ]
  },
  {
    "generated_at": "2026-06-08T20:01:37Z",
    "anchor_date": "2026-06-08",
    "forecast": [
      {
        "day": 1,
        "date": "2026-06-09",
        "flow_m3s": 1241.0,
        "level_m": 20.054
      },
      {
        "day": 2,
        "date": "2026-06-10",
        "flow_m3s": 1215.9,
        "level_m": 20.036
      },
      {
        "day": 3,
        "date": "2026-06-11",
        "flow_m3s": 1254.2,
        "level_m": 20.076
      },
      {
        "day": 4,
        "date": "2026-06-12",
        "flow_m3s": 1269.1,
        "level_m": 20.1
      },
      {
        "day": 5,
        "date": "2026-06-13",
        "flow_m3s": 1227.3,
        "level_m": 20.082
      },
      {
        "day": 6,
        "date": "2026-06-14",
        "flow_m3s": 1237.8,
        "level_m": 20.023
      },
      {
        "day": 7,
        "date": "2026-06-15",
        "flow_m3s": 1174.8,
        "level_m": 19.978
      },
      {
        "day": 8,
        "date": "2026-06-16",
        "flow_m3s": 1132.9,
        "level_m": 19.964
      },
      {
        "day": 9,
        "date": "2026-06-17",
        "flow_m3s": 1166.0,
        "level_m": 19.967
      },
      {
        "day": 10,
        "date": "2026-06-18",
        "flow_m3s": 1191.6,
        "level_m": 19.911
      }
    ]
  },
  {
    "generated_at": "2026-06-09T20:01:41Z",
    "anchor_date": "2026-06-09",
    "forecast": [
      {
        "day": 1,
        "date": "2026-06-10",
        "flow_m3s": 1173.4,
        "level_m": 19.963
      },
      {
        "day": 2,
        "date": "2026-06-11",
        "flow_m3s": 1201.4,
        "level_m": 20.0
      },
      {
        "day": 3,
        "date": "2026-06-12",
        "flow_m3s": 1225.6,
        "level_m": 19.99
      },
      {
        "day": 4,
        "date": "2026-06-13",
        "flow_m3s": 1233.9,
        "level_m": 20.043
      },
      {
        "day": 5,
        "date": "2026-06-14",
        "flow_m3s": 1197.0,
        "level_m": 19.999
      },
      {
        "day": 6,
        "date": "2026-06-15",
        "flow_m3s": 1191.2,
        "level_m": 19.992
      },
      {
        "day": 7,
        "date": "2026-06-16",
        "flow_m3s": 1144.3,
        "level_m": 19.932
      },
      {
        "day": 8,
        "date": "2026-06-17",
        "flow_m3s": 1086.7,
        "level_m": 19.925
      },
      {
        "day": 9,
        "date": "2026-06-18",
        "flow_m3s": 1114.1,
        "level_m": 19.842
      },
      {
        "day": 10,
        "date": "2026-06-19",
        "flow_m3s": 1094.5,
        "level_m": 19.845
      }
    ]
  },
  {
    "generated_at": "2026-06-10T20:01:28Z",
    "anchor_date": "2026-06-10",
    "forecast": [
      {
        "day": 1,
        "date": "2026-06-11",
        "flow_m3s": 1254.9,
        "level_m": 20.02
      },
      {
        "day": 2,
        "date": "2026-06-12",
        "flow_m3s": 1237.6,
        "level_m": 20.063
      },
      {
        "day": 3,
        "date": "2026-06-13",
        "flow_m3s": 1223.1,
        "level_m": 20.027
      },
      {
        "day": 4,
        "date": "2026-06-14",
        "flow_m3s": 1249.6,
        "level_m": 20.066
      },
      {
        "day": 5,
        "date": "2026-06-15",
        "flow_m3s": 1229.9,
        "level_m": 20.009
      },
      {
        "day": 6,
        "date": "2026-06-16",
        "flow_m3s": 1260.6,
        "level_m": 20.051
      },
      {
        "day": 7,
        "date": "2026-06-17",
        "flow_m3s": 1243.5,
        "level_m": 20.077
      },
      {
        "day": 8,
        "date": "2026-06-18",
        "flow_m3s": 1222.4,
        "level_m": 20.146
      },
      {
        "day": 9,
        "date": "2026-06-19",
        "flow_m3s": 1254.0,
        "level_m": 20.039
      },
      {
        "day": 10,
        "date": "2026-06-20",
        "flow_m3s": 1249.0,
        "level_m": 19.97
      }
    ]
  },
  {
    "generated_at": "2026-06-11T20:01:55Z",
    "anchor_date": "2026-06-11",
    "forecast": [
      {
        "day": 1,
        "date": "2026-06-12",
        "flow_m3s": 1179.7,
        "level_m": 19.992
      },
      {
        "day": 2,
        "date": "2026-06-13",
        "flow_m3s": 1239.5,
        "level_m": 20.033
      },
      {
        "day": 3,
        "date": "2026-06-14",
        "flow_m3s": 1282.6,
        "level_m": 20.059
      },
      {
        "day": 4,
        "date": "2026-06-15",
        "flow_m3s": 1249.4,
        "level_m": 20.065
      },
      {
        "day": 5,
        "date": "2026-06-16",
        "flow_m3s": 1219.4,
        "level_m": 19.974
      },
      {
        "day": 6,
        "date": "2026-06-17",
        "flow_m3s": 1165.9,
        "level_m": 19.991
      },
      {
        "day": 7,
        "date": "2026-06-18",
        "flow_m3s": 1192.8,
        "level_m": 20.034
      },
      {
        "day": 8,
        "date": "2026-06-19",
        "flow_m3s": 1190.4,
        "level_m": 20.067
      },
      {
        "day": 9,
        "date": "2026-06-20",
        "flow_m3s": 1268.6,
        "level_m": 20.015
      },
      {
        "day": 10,
        "date": "2026-06-21",
        "flow_m3s": 1232.8,
        "level_m": 20.094
      }
    ]
  },
  {
    "generated_at": "2026-06-12T11:01:28Z",
    "anchor_date": "2026-06-12",
    "forecast": [
      {
        "day": 1,
        "date": "2026-06-13",
        "flow_m3s": 1218.6,
        "level_m": 20.04
      },
      {
        "day": 2,
        "date": "2026-06-14",
        "flow_m3s": 1238.9,
        "level_m": 20.049
      },
      {
        "day": 3,
        "date": "2026-06-15",
        "flow_m3s": 1291.0,
        "level_m": 20.12
      },
      {
        "day": 4,
        "date": "2026-06-16",
        "flow_m3s": 1287.3,
        "level_m": 20.148
      },
      {
        "day": 5,
        "date": "2026-06-17",
        "flow_m3s": 1249.6,
        "level_m": 20.041
      },
      {
        "day": 6,
        "date": "2026-06-18",
        "flow_m3s": 1292.5,
        "level_m": 20.074
      },
      {
        "day": 7,
        "date": "2026-06-19",
        "flow_m3s": 1328.6,
        "level_m": 20.147
      },
      {
        "day": 8,
        "date": "2026-06-20",
        "flow_m3s": 1295.5,
        "level_m": 20.212
      },
      {
        "day": 9,
        "date": "2026-06-21",
        "flow_m3s": 1279.4,
        "level_m": 20.106
      },
      {
        "day": 10,
        "date": "2026-06-22",
        "flow_m3s": 1251.2,
        "level_m": 20.067
      }
    ]
  },
  {
    "generated_at": "2026-06-23T00:54:06Z",
    "anchor_date": "2026-06-22",
    "forecast": [
      {
        "day": 1,
        "date": "2026-06-23",
        "flow_m3s": 1316.0,
        "level_m": 20.128
      },
      {
        "day": 2,
        "date": "2026-06-24",
        "flow_m3s": 1238.3,
        "level_m": 20.102
      },
      {
        "day": 3,
        "date": "2026-06-25",
        "flow_m3s": 1293.4,
        "level_m": 20.107
      },
      {
        "day": 4,
        "date": "2026-06-26",
        "flow_m3s": 1338.7,
        "level_m": 20.146
      },
      {
        "day": 5,
        "date": "2026-06-27",
        "flow_m3s": 1284.3,
        "level_m": 20.083
      },
      {
        "day": 6,
        "date": "2026-06-28",
        "flow_m3s": 1238.4,
        "level_m": 20.048
      },
      {
        "day": 7,
        "date": "2026-06-29",
        "flow_m3s": 1224.0,
        "level_m": 20.131
      },
      {
        "day": 8,
        "date": "2026-06-30",
        "flow_m3s": 1260.6,
        "level_m": 20.058
      },
      {
        "day": 9,
        "date": "2026-07-01",
        "flow_m3s": 1217.3,
        "level_m": 20.018
      },
      {
        "day": 10,
        "date": "2026-07-02",
        "flow_m3s": 1176.4,
        "level_m": 19.942
      }
    ]
  },
  {
    "generated_at": "2026-06-23T23:35:57Z",
    "anchor_date": "2026-06-23",
    "forecast": [
      {
        "day": 1,
        "date": "2026-06-24",
        "flow_m3s": 1326.9,
        "level_m": 20.15
      },
      {
        "day": 2,
        "date": "2026-06-25",
        "flow_m3s": 1289.5,
        "level_m": 20.169
      },
      {
        "day": 3,
        "date": "2026-06-26",
        "flow_m3s": 1328.4,
        "level_m": 20.206
      },
      {
        "day": 4,
        "date": "2026-06-27",
        "flow_m3s": 1365.7,
        "level_m": 20.228
      },
      {
        "day": 5,
        "date": "2026-06-28",
        "flow_m3s": 1329.7,
        "level_m": 20.092
      },
      {
        "day": 6,
        "date": "2026-06-29",
        "flow_m3s": 1309.3,
        "level_m": 20.106
      },
      {
        "day": 7,
        "date": "2026-06-30",
        "flow_m3s": 1299.5,
        "level_m": 20.13
      },
      {
        "day": 8,
        "date": "2026-07-01",
        "flow_m3s": 1300.6,
        "level_m": 20.058
      },
      {
        "day": 9,
        "date": "2026-07-02",
        "flow_m3s": 1207.8,
        "level_m": 20.041
      },
      {
        "day": 10,
        "date": "2026-07-03",
        "flow_m3s": 1169.4,
        "level_m": 19.932
      }
    ]
  },
  {
    "generated_at": "2026-06-24T20:01:29Z",
    "anchor_date": "2026-06-24",
    "forecast": [
      {
        "day": 1,
        "date": "2026-06-25",
        "flow_m3s": 1275.2,
        "level_m": 20.12
      },
      {
        "day": 2,
        "date": "2026-06-26",
        "flow_m3s": 1290.4,
        "level_m": 20.116
      },
      {
        "day": 3,
        "date": "2026-06-27",
        "flow_m3s": 1337.7,
        "level_m": 20.176
      },
      {
        "day": 4,
        "date": "2026-06-28",
        "flow_m3s": 1359.7,
        "level_m": 20.22
      },
      {
        "day": 5,
        "date": "2026-06-29",
        "flow_m3s": 1346.7,
        "level_m": 20.093
      },
      {
        "day": 6,
        "date": "2026-06-30",
        "flow_m3s": 1312.4,
        "level_m": 20.08
      },
      {
        "day": 7,
        "date": "2026-07-01",
        "flow_m3s": 1306.5,
        "level_m": 20.14
      },
      {
        "day": 8,
        "date": "2026-07-02",
        "flow_m3s": 1237.7,
        "level_m": 20.048
      },
      {
        "day": 9,
        "date": "2026-07-03",
        "flow_m3s": 1194.6,
        "level_m": 19.985
      },
      {
        "day": 10,
        "date": "2026-07-04",
        "flow_m3s": 1148.9,
        "level_m": 19.944
      }
    ]
  },
  {
    "generated_at": "2026-06-25T20:01:57Z",
    "anchor_date": "2026-06-25",
    "forecast": [
      {
        "day": 1,
        "date": "2026-06-26",
        "flow_m3s": 1216.2,
        "level_m": 20.035
      },
      {
        "day": 2,
        "date": "2026-06-27",
        "flow_m3s": 1194.6,
        "level_m": 20.055
      },
      {
        "day": 3,
        "date": "2026-06-28",
        "flow_m3s": 1213.1,
        "level_m": 20.058
      },
      {
        "day": 4,
        "date": "2026-06-29",
        "flow_m3s": 1228.0,
        "level_m": 20.102
      },
      {
        "day": 5,
        "date": "2026-06-30",
        "flow_m3s": 1211.3,
        "level_m": 19.961
      },
      {
        "day": 6,
        "date": "2026-07-01",
        "flow_m3s": 1210.6,
        "level_m": 20.014
      },
      {
        "day": 7,
        "date": "2026-07-02",
        "flow_m3s": 1177.1,
        "level_m": 20.022
      },
      {
        "day": 8,
        "date": "2026-07-03",
        "flow_m3s": 1143.6,
        "level_m": 19.973
      },
      {
        "day": 9,
        "date": "2026-07-04",
        "flow_m3s": 1138.4,
        "level_m": 20.002
      },
      {
        "day": 10,
        "date": "2026-07-05",
        "flow_m3s": 1150.3,
        "level_m": 19.961
      }
    ]
  },
  {
    "generated_at": "2026-06-26T20:00:57Z",
    "anchor_date": "2026-06-26",
    "forecast": [
      {
        "day": 1,
        "date": "2026-06-27",
        "flow_m3s": 1192.2,
        "level_m": 19.98
      },
      {
        "day": 2,
        "date": "2026-06-28",
        "flow_m3s": 1171.2,
        "level_m": 20.001
      },
      {
        "day": 3,
        "date": "2026-06-29",
        "flow_m3s": 1148.0,
        "level_m": 19.962
      },
      {
        "day": 4,
        "date": "2026-06-30",
        "flow_m3s": 1170.3,
        "level_m": 19.969
      },
      {
        "day": 5,
        "date": "2026-07-01",
        "flow_m3s": 1137.7,
        "level_m": 19.918
      },
      {
        "day": 6,
        "date": "2026-07-02",
        "flow_m3s": 1167.0,
        "level_m": 19.981
      },
      {
        "day": 7,
        "date": "2026-07-03",
        "flow_m3s": 1127.9,
        "level_m": 19.926
      },
      {
        "day": 8,
        "date": "2026-07-04",
        "flow_m3s": 1156.7,
        "level_m": 19.905
      },
      {
        "day": 9,
        "date": "2026-07-05",
        "flow_m3s": 1072.3,
        "level_m": 19.896
      },
      {
        "day": 10,
        "date": "2026-07-06",
        "flow_m3s": 1062.7,
        "level_m": 19.827
      }
    ]
  },
  {
    "generated_at": "2026-06-27T20:01:17Z",
    "anchor_date": "2026-06-27",
    "forecast": [
      {
        "day": 1,
        "date": "2026-06-28",
        "flow_m3s": 1154.1,
        "level_m": 19.95
      },
      {
        "day": 2,
        "date": "2026-06-29",
        "flow_m3s": 1125.2,
        "level_m": 19.972
      },
      {
        "day": 3,
        "date": "2026-06-30",
        "flow_m3s": 1124.1,
        "level_m": 19.91
      },
      {
        "day": 4,
        "date": "2026-07-01",
        "flow_m3s": 1099.7,
        "level_m": 19.918
      },
      {
        "day": 5,
        "date": "2026-07-02",
        "flow_m3s": 1074.0,
        "level_m": 19.865
      },
      {
        "day": 6,
        "date": "2026-07-03",
        "flow_m3s": 1061.1,
        "level_m": 19.861
      },
      {
        "day": 7,
        "date": "2026-07-04",
        "flow_m3s": 1042.5,
        "level_m": 19.857
      },
      {
        "day": 8,
        "date": "2026-07-05",
        "flow_m3s": 1032.6,
        "level_m": 19.823
      },
      {
        "day": 9,
        "date": "2026-07-06",
        "flow_m3s": 1019.7,
        "level_m": 19.789
      },
      {
        "day": 10,
        "date": "2026-07-07",
        "flow_m3s": 999.3,
        "level_m": 19.759
      }
    ]
  },
  {
    "generated_at": "2026-06-28T20:01:15Z",
    "anchor_date": "2026-06-28",
    "forecast": [
      {
        "day": 1,
        "date": "2026-06-29",
        "flow_m3s": 1123.9,
        "level_m": 19.9
      },
      {
        "day": 2,
        "date": "2026-06-30",
        "flow_m3s": 1096.5,
        "level_m": 19.914
      },
      {
        "day": 3,
        "date": "2026-07-01",
        "flow_m3s": 1115.7,
        "level_m": 19.906
      },
      {
        "day": 4,
        "date": "2026-07-02",
        "flow_m3s": 1148.8,
        "level_m": 19.962
      },
      {
        "day": 5,
        "date": "2026-07-03",
        "flow_m3s": 1171.3,
        "level_m": 19.972
      },
      {
        "day": 6,
        "date": "2026-07-04",
        "flow_m3s": 1129.8,
        "level_m": 19.914
      },
      {
        "day": 7,
        "date": "2026-07-05",
        "flow_m3s": 1152.7,
        "level_m": 19.971
      },
      {
        "day": 8,
        "date": "2026-07-06",
        "flow_m3s": 1109.8,
        "level_m": 19.924
      },
      {
        "day": 9,
        "date": "2026-07-07",
        "flow_m3s": 1099.0,
        "level_m": 19.837
      },
      {
        "day": 10,
        "date": "2026-07-08",
        "flow_m3s": 1057.9,
        "level_m": 19.851
      }
    ]
  },
  {
    "generated_at": "2026-06-29T20:01:24Z",
    "anchor_date": "2026-06-29",
    "forecast": [
      {
        "day": 1,
        "date": "2026-06-30",
        "flow_m3s": 1091.9,
        "level_m": 19.87
      },
      {
        "day": 2,
        "date": "2026-07-01",
        "flow_m3s": 1132.1,
        "level_m": 19.983
      },
      {
        "day": 3,
        "date": "2026-07-02",
        "flow_m3s": 1159.9,
        "level_m": 19.949
      },
      {
        "day": 4,
        "date": "2026-07-03",
        "flow_m3s": 1180.2,
        "level_m": 19.973
      },
      {
        "day": 5,
        "date": "2026-07-04",
        "flow_m3s": 1145.0,
        "level_m": 19.894
      },
      {
        "day": 6,
        "date": "2026-07-05",
        "flow_m3s": 1107.8,
        "level_m": 19.903
      },
      {
        "day": 7,
        "date": "2026-07-06",
        "flow_m3s": 1169.5,
        "level_m": 19.966
      },
      {
        "day": 8,
        "date": "2026-07-07",
        "flow_m3s": 1140.0,
        "level_m": 19.92
      },
      {
        "day": 9,
        "date": "2026-07-08",
        "flow_m3s": 1077.3,
        "level_m": 19.865
      },
      {
        "day": 10,
        "date": "2026-07-09",
        "flow_m3s": 1088.1,
        "level_m": 19.861
      }
    ]
  },
  {
    "generated_at": "2026-06-30T11:02:34Z",
    "anchor_date": "2026-06-30",
    "forecast": [
      {
        "day": 1,
        "date": "2026-07-01",
        "flow_m3s": 1042.0,
        "level_m": 19.811
      },
      {
        "day": 2,
        "date": "2026-07-02",
        "flow_m3s": 1020.8,
        "level_m": 19.781
      },
      {
        "day": 3,
        "date": "2026-07-03",
        "flow_m3s": 996.1,
        "level_m": 19.74
      },
      {
        "day": 4,
        "date": "2026-07-04",
        "flow_m3s": 1001.9,
        "level_m": 19.78
      },
      {
        "day": 5,
        "date": "2026-07-05",
        "flow_m3s": 1029.6,
        "level_m": 19.811
      },
      {
        "day": 6,
        "date": "2026-07-06",
        "flow_m3s": 979.6,
        "level_m": 19.735
      },
      {
        "day": 7,
        "date": "2026-07-07",
        "flow_m3s": 968.8,
        "level_m": 19.732
      },
      {
        "day": 8,
        "date": "2026-07-08",
        "flow_m3s": 927.7,
        "level_m": 19.712
      },
      {
        "day": 9,
        "date": "2026-07-09",
        "flow_m3s": 945.6,
        "level_m": 19.655
      },
      {
        "day": 10,
        "date": "2026-07-10",
        "flow_m3s": 929.1,
        "level_m": 19.641
      }
    ]
  }
]