{
  "generated_at": "2026-05-01T11:01:18Z",
  "anchor_date": "2026-05-01",
  "flood_risk": {
    "concern": true,
    "near_flood": false,
    "max_predicted_flow_m3s": 2649.3
  },
  "forecast": [
    {
      "day": 1,
      "date": "2026-05-02",
      "flow_m3s": 2649.3,
      "level_m": 21.807
    },
    {
      "day": 2,
      "date": "2026-05-03",
      "flow_m3s": 2644.4,
      "level_m": 21.743
    },
    {
      "day": 3,
      "date": "2026-05-04",
      "flow_m3s": 2601.0,
      "level_m": 21.696
    },
    {
      "day": 4,
      "date": "2026-05-05",
      "flow_m3s": 2481.4,
      "level_m": 21.816
    },
    {
      "day": 5,
      "date": "2026-05-06",
      "flow_m3s": 2534.5,
      "level_m": 21.71
    }
  ]
}